Metadata-Version: 1.2
Name: django-form-tags
Version: 2.0
Summary: Django templatetags to easily render fieldholders, fieldwrappers and fields.
Home-page: https://gitlab.com/mediamoose/django-form-tags/tree/v2.0
Author: Sven Groot (Mediamoose)
Author-email: sven@mediamoose.nl
License: MIT
Download-URL: https://gitlab.com/mediamoose/django-form-tags/repository/v2.0/archive.tar.gz
Keywords: forms,templatetags,django
Platform: UNKNOWN
Classifier: Development Status :: 3 - Alpha
Classifier: Framework :: Django
Classifier: Framework :: Django :: 1.11
Classifier: Framework :: Django :: 2.0
Classifier: Framework :: Django :: 2.1
Classifier: Framework :: Django :: 2.2
Classifier: Intended Audience :: Developers
Classifier: License :: OSI Approved :: MIT License
Classifier: Natural Language :: English
Classifier: Operating System :: POSIX :: Linux
Classifier: Programming Language :: Python
Classifier: Programming Language :: Python :: 3.6
Classifier: Programming Language :: Python :: 3.7
Requires-Python: >=3.6
